exceptions_and_logging/__init__.py
exceptions_and_logging/apps.py
exceptions_and_logging/exception_handler.py
exceptions_and_logging/exceptions.py
exceptions_and_logging/logging_settings.py
exceptions_and_logging/settings.py
exceptions_and_logging-0.0.2.dist-info/LICENSE.txt
exceptions_and_logging-0.0.2.dist-info/METADATA
exceptions_and_logging-0.0.2.dist-info/WHEEL
exceptions_and_logging-0.0.2.dist-info/top_level.txt
exceptions_and_logging-0.0.2.dist-info/RECORD
