Metadata-Version: 2.1
Name: exceptions-and-logging
Version: 0.0.2
Summary: A Django app for logging custom application errors
Home-page: https://github.com/Agamiru/exceptions_and_logging
Author: Chidi Nnadi
Author-email: chidinnaemekannadi@gmail.com
License: UNKNOWN
Platform: UNKNOWN
Classifier: Programming Language :: Python :: 3
Classifier: License :: OSI Approved :: MIT License
Classifier: Operating System :: OS Independent
Classifier: Framework :: Django :: 3.0
Requires-Python: >=3.6
